[
  {
    "id": "HkqEDLvxE",
    "name": "Reuben Kaur",
    "gender": "male",
    "image": "male/01.jpg",
    "from": "Moscow",
    "birthday": "1962-02-23",
    "deathday": "1992-08-13",
    "parents": [
      {
        "id": "011jVS4rb",
        "type": "blood"
      },
      {
        "id": "PXACjDxmR",
        "type": "blood"
      }
    ],
    "siblings": [
      {
        "id": "kuVISwh7w",
        "type": "blood"
      },
      {
        "id": "UIEjvLJMd",
        "type": "blood"
      },
      {
        "id": "ZVi8fWDBx",
        "type": "blood"
      }
    ],
    "spouses": [],
    "children": []
  },
  {
    "id": "011jVS4rb",
    "name": "Kyle Stewart",
    "gender": "male",
    "image": "male/02.jpg",
    "from": "Moscow",
    "birthday": "1959-04-15",
    "parents": [
      {
        "id": "ypu71w9_Q",
        "type": "blood"
      },
      {
        "id": "GEf8zF7A4",
        "type": "blood"
      }
    ],
    "children": [
      {
        "id": "HkqEDLvxE",
        "type": "blood"
      },
      {
        "id": "kuVISwh7w",
        "type": "blood"
      },
      {
        "id": "UIEjvLJMd",
        "type": "blood"
      },
      {
        "id": "ZVi8fWDBx",
        "type": "blood"
      }
    ],
    "siblings": [],
    "spouses": [
      {
        "id": "PXACjDxmR",
        "type": "married"
      }
    ]
  },
  {
    "id": "PXACjDxmR",
    "name": "Megan Roberts",
    "gender": "female",
    "image": "female/01.jpg",
    "from": "Roma",
    "birthday": "1965-03-04",
    "parents": [
      {
        "id": "2DlrR0fK8",
        "type": "blood"
      }
    ],
    "children": [
      {
        "id": "HkqEDLvxE",
        "type": "blood"
      },
      {
        "id": "kuVISwh7w",
        "type": "blood"
      },
      {
        "id": "UIEjvLJMd",
        "type": "blood"
      },
      {
        "id": "ZVi8fWDBx",
        "type": "blood"
      }
    ],
    "siblings": [
      {
        "id": "H-06WvsfJ",
        "type": "blood"
      }
    ],
    "spouses": [
      {
        "id": "011jVS4rb",
        "type": "married"
      }
    ]
  },
  {
    "id": "kuVISwh7w",
    "name": "Charlie Woods",
    "gender": "male",
    "image": "male/11.jpg",
    "from": "Roma",
    "birthday": "1973-05-22",
    "parents": [
      {
        "id": "011jVS4rb",
        "type": "blood"
      },
      {
        "id": "PXACjDxmR",
        "type": "blood"
      }
    ],
    "children": [
      {
        "id": "Fbc9iwnJl",
        "type": "blood"
      }
    ],
    "siblings": [
      {
        "id": "HkqEDLvxE",
        "type": "blood"
      },
      {
        "id": "UIEjvLJMd",
        "type": "blood"
      },
      {
        "id": "ZVi8fWDBx",
        "type": "blood"
      }
    ],
    "spouses": [
      {
        "id": "vRSjcaDGj",
        "type": "married"
      }
    ]
  },
  {
    "id": "UIEjvLJMd",
    "name": "Sarah Carter",
    "gender": "female",
    "image": "female/02.jpg",
    "from": "Roma",
    "birthday": "1975-09-16",
    "parents": [
      {
        "id": "011jVS4rb",
        "type": "blood"
      },
      {
        "id": "PXACjDxmR",
        "type": "blood"
      }
    ],
    "children": [
      {
        "id": "6_OTJvbvS",
        "type": "blood"
      },
      {
        "id": "JhSCcdFEP",
        "type": "blood"
      },
      {
        "id": "6hNxNY1-I",
        "type": "blood"
      }
    ],
    "siblings": [
      {
        "id": "HkqEDLvxE",
        "type": "blood"
      },
      {
        "id": "kuVISwh7w",
        "type": "blood"
      },
      {
        "id": "ZVi8fWDBx",
        "type": "blood"
      }
    ],
    "spouses": [
      {
        "id": "RZbkr5vAi",
        "type": "married"
      }
    ]
  },
  {
    "id": "RZbkr5vAi",
    "name": "Reece Cunningham",
    "gender": "male",
    "image": "male/03.jpg",
    "from": "Moscow",
    "birthday": "1975-05-11",
    "parents": [],
    "children": [
      {
        "id": "6_OTJvbvS",
        "type": "blood"
      },
      {
        "id": "JhSCcdFEP",
        "type": "blood"
      },
      {
        "id": "6hNxNY1-I",
        "type": "blood"
      }
    ],
    "siblings": [],
    "spouses": [
      {
        "id": "UIEjvLJMd",
        "type": "married"
      }
    ]
  },
  {
    "id": "vRSjcaDGj",
    "name": "Cerys Grant",
    "gender": "female",
    "image": "female/03.jpg",
    "from": "New York",
    "birthday": "1965-03-13",
    "parents": [
      {
        "id": "6vASIIxhd",
        "type": "blood"
      },
      {
        "id": "iFiwqrWx-",
        "type": "blood"
      }
    ],
    "children": [
      {
        "id": "Fbc9iwnJl",
        "type": "blood"
      }
    ],
    "siblings": [],
    "spouses": [
      {
        "id": "kuVISwh7w",
        "type": "married"
      }
    ]
  },
  {
    "id": "Fbc9iwnJl",
    "name": "Megan Owen",
    "gender": "female",
    "image": "female/04.jpg",
    "from": "New York",
    "birthday": "1996-06-12",
    "parents": [
      {
        "id": "kuVISwh7w",
        "type": "blood"
      },
      {
        "id": "vRSjcaDGj",
        "type": "blood"
      }
    ],
    "children": [],
    "siblings": [],
    "spouses": []
  },
  {
    "id": "ypu71w9_Q",
    "name": "Jasper Garcia",
    "gender": "male",
    "image": "male/04.jpg",
    "from": "New York",
    "birthday": "1938-03-14",
    "deathday": "2001-04-12",
    "parents": [
      {
        "id": "TsyAkbF89",
        "type": "blood"
      },
      {
        "id": "T54Km7uOC",
        "type": "blood"
      }
    ],
    "children": [
      {
        "id": "011jVS4rb",
        "type": "blood"
      }
    ],
    "siblings": [],
    "spouses": [
      {
        "id": "GEf8zF7A4",
        "type": "married"
      }
    ]
  },
  {
    "id": "GEf8zF7A4",
    "name": "Mya Johnston",
    "gender": "female",
    "image": "female/05.jpg",
    "from": "New York",
    "birthday": "1935-09-29",
    "parents": [
      {
        "id": "gsgwGS_Kw",
        "type": "blood"
      },
      {
        "id": "ZgTZx9uXQ",
        "type": "blood"
      }
    ],
    "children": [
      {
        "id": "011jVS4rb",
        "type": "blood"
      }
    ],
    "siblings": [],
    "spouses": [
      {
        "id": "ypu71w9_Q",
        "type": "married"
      }
    ]
  },
  {
    "id": "2DlrR0fK8",
    "name": "Malik Melton",
    "gender": "male",
    "image": "male/05.jpg",
    "from": "Barcelona",
    "birthday": "1945-09-21",
    "parents": [],
    "children": [
      {
        "id": "PXACjDxmR",
        "type": "blood"
      },
      {
        "id": "H-06WvsfJ",
        "type": "blood"
      }
    ],
    "siblings": [],
    "spouses": []
  },
  {
    "id": "gsgwGS_Kw",
    "name": "Bradley Decker",
    "gender": "male",
    "image": "male/06.jpg",
    "from": "Barcelona",
    "birthday": "1925-03-22",
    "deathday": "1990-07-06",
    "parents": [],
    "children": [
      {
        "id": "GEf8zF7A4",
        "type": "blood"
      }
    ],
    "siblings": [],
    "spouses": [
      {
        "id": "ZgTZx9uXQ",
        "type": "married"
      }
    ]
  },
  {
    "id": "ZgTZx9uXQ",
    "name": "Zaniyah Compton",
    "gender": "female",
    "from": "New York",
    "birthday": "1927-07-17",
    "deathday": "1985-06-04",
    "parents": [],
    "children": [
      {
        "id": "GEf8zF7A4",
        "type": "blood"
      }
    ],
    "siblings": [],
    "spouses": [
      {
        "id": "gsgwGS_Kw",
        "type": "married"
      }
    ]
  },
  {
    "id": "ZVi8fWDBx",
    "name": "Deegan Pace",
    "gender": "male",
    "image": "male/07.jpg",
    "from": "Barcelona",
    "birthday": "1987-03-25",
    "parents": [
      {
        "id": "011jVS4rb",
        "type": "blood"
      },
      {
        "id": "PXACjDxmR",
        "type": "blood"
      }
    ],
    "children": [],
    "siblings": [
      {
        "id": "HkqEDLvxE",
        "type": "blood"
      },
      {
        "id": "kuVISwh7w",
        "type": "blood"
      },
      {
        "id": "UIEjvLJMd",
        "type": "blood"
      }
    ],
    "spouses": [
      {
        "id": "wJ1EBvc5m",
        "type": "married"
      }
    ]
  },
  {
    "id": "6_OTJvbvS",
    "name": "Keenan Hardin",
    "gender": "male",
    "image": "male/08.jpg",
    "from": "Berlin",
    "birthday": "2006-11-11",
    "parents": [
      {
        "id": "RZbkr5vAi",
        "type": "blood"
      },
      {
        "id": "UIEjvLJMd",
        "type": "blood"
      }
    ],
    "children": [],
    "siblings": [
      {
        "id": "JhSCcdFEP",
        "type": "blood"
      },
      {
        "id": "6hNxNY1-I",
        "type": "blood"
      }
    ],
    "spouses": []
  },
  {
    "id": "JhSCcdFEP",
    "name": "Allie Richards",
    "gender": "female",
    "image": "female/07.jpg",
    "from": "Barcelona",
    "birthday": "1991-10-12",
    "parents": [
      {
        "id": "RZbkr5vAi",
        "type": "blood"
      },
      {
        "id": "UIEjvLJMd",
        "type": "blood"
      }
    ],
    "children": [
      {
        "id": "Z0QA5oKks",
        "type": "blood"
      }
    ],
    "siblings": [
      {
        "id": "6_OTJvbvS",
        "type": "blood"
      },
      {
        "id": "6hNxNY1-I",
        "type": "blood"
      }
    ],
    "spouses": [
      {
        "id": "ilad8NH6g",
        "type": "married"
      }
    ]
  },
  {
    "id": "6hNxNY1-I",
    "name": "Jay Walker",
    "gender": "male",
    "image": "male/09.jpg",
    "from": "Barcelona",
    "birthday": "1995-10-22",
    "parents": [
      {
        "id": "RZbkr5vAi",
        "type": "blood"
      },
      {
        "id": "UIEjvLJMd",
        "type": "blood"
      }
    ],
    "children": [],
    "siblings": [
      {
        "id": "6_OTJvbvS",
        "type": "blood"
      },
      {
        "id": "JhSCcdFEP",
        "type": "blood"
      }
    ],
    "spouses": []
  },
  {
    "id": "ilad8NH6g",
    "name": "Theo Simpson",
    "gender": "male",
    "image": "male/10.jpg",
    "from": "Berlin",
    "birthday": "1992-04-10",
    "parents": [],
    "children": [
      {
        "id": "Z0QA5oKks",
        "type": "blood"
      }
    ],
    "siblings": [],
    "spouses": [
      {
        "id": "JhSCcdFEP",
        "type": "married"
      }
    ]
  },
  {
    "id": "Z0QA5oKks",
    "name": "Toby Burton",
    "gender": "male",
    "image": "male/12.jpg",
    "from": "Berlin",
    "birthday": "2008-03-15",
    "parents": [
      {
        "id": "ilad8NH6g",
        "type": "blood"
      },
      {
        "id": "JhSCcdFEP",
        "type": "blood"
      }
    ],
    "children": [],
    "siblings": [],
    "spouses": []
  },
  {
    "id": "wJ1EBvc5m",
    "name": "Katherine Aguirre",
    "gender": "female",
    "image": "female/08.jpg",
    "from": "Paris",
    "birthday": "1987-05-16",
    "parents": [],
    "children": [],
    "siblings": [],
    "spouses": [
      {
        "id": "ZVi8fWDBx",
        "type": "married"
      }
    ]
  },
  {
    "id": "TsyAkbF89",
    "name": "Desmond Leonard",
    "gender": "male",
    "image": "male/13.jpg",
    "from": "Paris",
    "birthday": "1915-06-29",
    "deathday": "1992-01-15",
    "parents": [],
    "children": [
      {
        "id": "ypu71w9_Q",
        "type": "blood"
      }
    ],
    "siblings": [],
    "spouses": [
      {
        "id": "T54Km7uOC",
        "type": "married"
      }
    ]
  },
  {
    "id": "T54Km7uOC",
    "name": "Ciara Harvey",
    "gender": "female",
    "image": "female/09.jpg",
    "from": "New York",
    "birthday": "1918-02-09",
    "deathday": "1962-06-16",
    "parents": [],
    "children": [
      {
        "id": "ypu71w9_Q",
        "type": "blood"
      }
    ],
    "siblings": [],
    "spouses": [
      {
        "id": "TsyAkbF89",
        "type": "married"
      }
    ]
  },
  {
    "id": "6vASIIxhd",
    "name": "Morgan Lowe",
    "gender": "male",
    "image": "male/14.jpg",
    "from": "New York",
    "birthday": "1965-03-24",
    "parents": [],
    "children": [
      {
        "id": "vRSjcaDGj",
        "type": "blood"
      }
    ],
    "siblings": [],
    "spouses": [
      {
        "id": "iFiwqrWx-",
        "type": "married"
      }
    ]
  },
  {
    "id": "iFiwqrWx-",
    "name": "Zaria Conrad",
    "gender": "female",
    "image": "female/10.jpg",
    "from": "New York",
    "birthday": "1965-03-26",
    "parents": [],
    "children": [
      {
        "id": "vRSjcaDGj",
        "type": "blood"
      }
    ],
    "siblings": [],
    "spouses": [
      {
        "id": "6vASIIxhd",
        "type": "married"
      }
    ]
  },
  {
    "id": "H-06WvsfJ",
    "name": "Ava Roberts",
    "gender": "female",
    "image": "female/11.jpg",
    "from": "Paris",
    "birthday": "1965-03-28",
    "parents": [
      {
        "id": "2DlrR0fK8",
        "type": "blood"
      }
    ],
    "children": [],
    "siblings": [
      {
        "id": "PXACjDxmR",
        "type": "blood"
      }
    ],
    "spouses": []
  }
]
